{
    "debug": true,
    "empire": {
        "api_key": "",
        "coin_value": 0.61403
    },
    "waxpeer": {
        "apiKey": "",
        "cacheList": 15,
        "buyOrderCheckPercentage": 10
    },
    "bid": {
        "enabled": false,
        "min_value": 50,
        "max_value": 200,
        "discount": 5,
        "buy_commodity": false,
        "buy_no_paint_items": false,
        "buy_knife_glove": false,
        "buy_stattrack": false,
        "validate_float": false,
        "wear_threshold": 80,
        "filter_by_wear": [
            "Battle-Scarred",
            "Field-Tested"
        ]
    },
    "print": {
        "bad_items": false
    }
}